randstadenterprise_edao_libraries/__init__.py
randstadenterprise_edao_libraries/domo_accounts.py
randstadenterprise_edao_libraries/domo_assets.py
randstadenterprise_edao_libraries/domo_datasets.py
randstadenterprise_edao_libraries/domo_groups.py
randstadenterprise_edao_libraries/domo_objects.py
randstadenterprise_edao_libraries/domo_roles.py
randstadenterprise_edao_libraries/domo_sandbox.py
randstadenterprise_edao_libraries/domo_users.py
randstadenterprise_edao_libraries/edao_helpers.py
randstadenterprise_edao_libraries/edao_http.py
randstadenterprise_edao_libraries/edao_logs.py
randstadenterprise_edao_libraries-0.1.35.dist-info/licenses/LICENSE
randstadenterprise_edao_libraries-0.1.35.dist-info/METADATA
randstadenterprise_edao_libraries-0.1.35.dist-info/WHEEL
randstadenterprise_edao_libraries-0.1.35.dist-info/top_level.txt
randstadenterprise_edao_libraries-0.1.35.dist-info/RECORD
