Metadata-Version: 2.4
Name: randstadenterprise_edao_libraries
Version: 0.1.35
Summary: Randstad Enterprise EDAO utility library.
Author-email: Mark Norman <mark.norman@randstadsourceright.com>
Classifier: Programming Language :: Python :: 3
Classifier: License :: OSI Approved :: MIT License
Classifier: Operating System :: OS Independent
Requires-Python: >=3.9
License-File: LICENSE
Dynamic: license-file
